src/__init__.py
src/lbfi.py
src/pyproject.toml
lbfi-0.3.4.dist-info/entry_points.txt
lbfi-0.3.4.dist-info/LICENSE
lbfi-0.3.4.dist-info/WHEEL
lbfi-0.3.4.dist-info/METADATA
lbfi-0.3.4.dist-info/RECORD
