Metadata-Version: 2.1
Name: lbfi
Version: 0.3.4
Summary: lbfi stands for Linux Bangla Font Installer. You can avail the fonts for your linux desktop easily with this tool. The main purpose of this tool is to easy installation of different and useful bangla fonts for your linux system.
License: MIT
Author: fahadahammed
Author-email: iamfahadahammed@gmail.com
Requires-Python: >=3.6,<4.0
Classifier: License :: OSI Approved :: MIT License
Classifier: Programming Language :: Python :: 3
Classifier: Programming Language :: Python :: 3.6
Classifier: Programming Language :: Python :: 3.7
Classifier: Programming Language :: Python :: 3.8
Classifier: Programming Language :: Python :: 3.9
Classifier: Programming Language :: Python :: 3.10
Classifier: Programming Language :: Python :: 3.11
